{
  "analysis": [
    {
      "line_number": "30",
      "maybe_in_function": "withdraw()",
      "pc": "0x2ab",
      "vuln_type": "Reentrancy"
    },
    {
      "line_number": "39",
      "maybe_in_function": "Command(address,bytes)",
      "pc": "0x4b8",
      "vuln_type": "Reentrancy"
    },
    {
      "line_number": "39",
      "maybe_in_function": "Command(address,bytes)",
      "pc": "0x4b8",
      "vuln_type": "Unchecked Low Level Call"
    },
    {
      "line_number": "21",
      "maybe_in_function": "GetFreebie()",
      "pc": "0x39a",
      "vuln_type": "Reentrancy"
    },
    {
      "line_number": "33",
      "maybe_in_function": "Command(address,bytes)",
      "pc": "0x110",
      "vuln_type": "Integer_Overflow"
    }
  ],
  "contract": "dataset/unchecked_low_level_calls/0xdb1c55f6926e7d847ddf8678905ad871a68199d2.sol",
  "duration": 11.477630376815796,
  "end": 1654106841.9067976,
  "exit_code": 0,
  "start": 1654106830.4291673,
  "tool": "conkas"
}