{
  "analysis": [
    {
      "callstack_depth_attack_vulnerability": false,
      "errors": [
        {
          "column": 17,
          "level": "Warning",
          "line": 24,
          "message": "Integer Overflow."
        },
        {
          "column": 10,
          "level": "Warning",
          "line": 20,
          "message": "Integer Overflow."
        }
      ],
      "evm_code_coverage": "80.7%",
      "file": "/data/mapping_write.sol",
      "integer_overflow": true,
      "integer_underflow": false,
      "name": "Map",
      "parity_multisig_bug_2": false,
      "re-entrancy_vulnerability": false,
      "timestamp_dependency": false,
      "transaction-ordering_dependence_tod": false
    }
  ],
  "contract": "dataset/access_control/mapping_write.sol",
  "duration": 4.003280401229858,
  "end": 1654181741.586205,
  "exit_code": 0,
  "start": 1654181737.5829246,
  "tool": "oyente"
}