{
  "analysis": [
    {
      "errors": [
        {
          "column": 10,
          "line": 22,
          "message": "overflow_bugs"
        },
        {
          "column": 10,
          "line": 16,
          "message": "overflow_bugs"
        },
        {
          "column": 10,
          "line": 27,
          "message": "time_dependency_bug"
        }
      ],
      "file": "/data/timelock.sol",
      "name": "TimeLock"
    }
  ],
  "contract": "dataset/arithmetic/timelock.sol",
  "duration": 4.1313066482543945,
  "end": 1654180934.8661163,
  "exit_code": 0,
  "start": 1654180930.7348096,
  "tool": "osiris"
}