{
  "analysis": [
    {
      "callstack_depth_attack_vulnerability": false,
      "errors": [
        {
          "column": 9,
          "level": "Warning",
          "line": 22,
          "message": "Integer Underflow."
        }
      ],
      "evm_code_coverage": "99.3%",
      "file": "/data/integer_overflow_multitx_onefunc_feasible.sol",
      "integer_overflow": false,
      "integer_underflow": true,
      "name": "IntegerOverflowMultiTxOneFuncFeasible",
      "parity_multisig_bug_2": false,
      "re-entrancy_vulnerability": false,
      "timestamp_dependency": false,
      "transaction-ordering_dependence_tod": false
    }
  ],
  "contract": "dataset/arithmetic/integer_overflow_multitx_onefunc_feasible.sol",
  "duration": 2.547870397567749,
  "end": 1654181752.4316294,
  "exit_code": 0,
  "start": 1654181749.883759,
  "tool": "oyente"
}